incentivedkutils.py
incentivedkutils-0.1.3.dist-info/LICENCE.txt
incentivedkutils-0.1.3.dist-info/METADATA
incentivedkutils-0.1.3.dist-info/WHEEL
incentivedkutils-0.1.3.dist-info/top_level.txt
incentivedkutils-0.1.3.dist-info/RECORD
