Metadata-Version: 2.1
Name: incentivedkutils
Version: 0.1.3
Summary: Incentive utilities
Author: Torben Franch
Author-email: torben@franch.eu
Classifier: License :: OSI Approved :: MIT License
Classifier: Programming Language :: Python :: 3.8
License-File: LICENCE.txt
Requires-Dist: tabulate
